sonsc_isi/__init__.py
sonsc_isi/clustering.py
sonsc_isi-0.1.dist-info/METADATA
sonsc_isi-0.1.dist-info/WHEEL
sonsc_isi-0.1.dist-info/top_level.txt
sonsc_isi-0.1.dist-info/RECORD
