Metadata-Version: 2.1
Name: sonsc-isi
Version: 0.1
Summary: Improved SONSC+ clustering evaluation using ISI (Improved SONSC Index)
Home-page: https://github.com/yourusername/sonsc-isi
Author: Your Name
Author-email: your.email@example.com
Classifier: Programming Language :: Python :: 3
Classifier: License :: OSI Approved :: MIT License
Classifier: Operating System :: OS Independent
Requires-Python: >=3.6
Requires-Dist: numpy
Requires-Dist: pandas
Requires-Dist: matplotlib
Requires-Dist: scikit-learn
Requires-Dist: tensorflow
